{"NtB6Gl2zyi": [], "NylVIMmHNb": [{"name": "stdout", "output_type": "stream", "text": ["Downloading https://www.cs.toronto.edu/~kriz/cifar-10-python.tar.gz to ./data/cifar-10-python.tar.gz\n"]}, {"name": "stderr", "output_type": "stream", "text": ["  0%|          | 0/170498071 [00:00<?, ?it/s]0.00s - Debugger warning: It seems that frozen modules are being used, which may\n", "0.00s - make the debugger miss breakpoints. Please pass -Xfrozen_modules=off\n", "0.00s - to python to disable frozen modules.\n", "0.00s - Note: Debugging will proceed. Set PYDEVD_DISABLE_FILE_VALIDATION=1 to disable this validation.\n", "100%|\u2588\u2588\u2588\u2588\u2588\u2588\u2588\u2588\u2588\u2588| 170498071/170498071 [00:56<00:00, 3035384.53it/s]\n"]}, {"name": "stdout", "output_type": "stream", "text": ["Extracting ./data/cifar-10-python.tar.gz to ./data\n", "Files already downloaded and verified\n"]}], "1jgqT8hvOh": [], "5DdueVwG8z": []}